manipulate_sequences/__init__.py
manipulate_sequences/fasta.py
manipulate_sequences/main.py
manipulate_sequences/sequence.py
manipulate_sequences-1.0.1.dist-info/METADATA
manipulate_sequences-1.0.1.dist-info/WHEEL
manipulate_sequences-1.0.1.dist-info/top_level.txt
manipulate_sequences-1.0.1.dist-info/RECORD
