Metadata-Version: 2.4
Name: manipulate_sequences
Version: 1.0.1
Summary: Utils function to analyze nucleotide sequences.
Author-email: Emma SOUFIR <emma.soufir@cirad.fr>
Requires-Dist: biopython
Requires-Dist: pandas
